WSIPeruDB/FilterDepartment.py
WSIPeruDB/__init__.py
WSIPeruDB/dataset_downloading.py
WSIPeruDB/departments_comparison.py
WSIPeruDB/lmwl_filtering.py
WSIPeruDB/map.py
WSIPeruDB/siteinformation_downloading.py
WSIPeruDB/temporalseries.py
WSIPeruDB-1.0.0.0.dist-info/METADATA
WSIPeruDB-1.0.0.0.dist-info/WHEEL
WSIPeruDB-1.0.0.0.dist-info/top_level.txt
WSIPeruDB-1.0.0.0.dist-info/RECORD
