Metadata-Version: 2.1
Name: WSIPeruDB
Version: 1.0.0.0
Summary: Water Stable Isotope Database in Peru
Home-page: https://github.com/karoru23/WSI-PeruDB
Author: Carol Romero
Author-email: romeroroldancarol@gmail.com
License: MIT license
Classifier: Programming Language :: Python :: 3
Classifier: License :: OSI Approved :: MIT License
Requires-Python: >=3.10
Requires-Dist: numpy
Requires-Dist: pandas
Requires-Dist: matplotlib
Requires-Dist: mysql-connector-python
Requires-Dist: folium
Requires-Dist: scikit-learn
Requires-Dist: plotly-express
Requires-Dist: ipywidgets
Requires-Dist: geopandas
Requires-Dist: xlsxwriter
